kelvin-3.3.0.data/purelib/kelvin/__init__.py
kelvin-3.3.0.data/purelib/kelvin/__kelvin__.py
kelvin-3.3.0.data/purelib/kelvin/analyze.py
kelvin-3.3.0.data/purelib/kelvin/build_exe.py
kelvin-3.3.0.data/purelib/kelvin/builder.py
kelvin-3.3.0.data/purelib/kelvin/compat2.py
kelvin-3.3.0.data/purelib/kelvin/compat3.py
kelvin-3.3.0.data/purelib/kelvin/dlls.py
kelvin-3.3.0.data/purelib/kelvin/imageutils.py
kelvin-3.3.0.data/purelib/kelvin/resources.py
kelvin-3.3.0.data/purelib/kelvin/utils.py
kelvin-3.3.0.data/purelib/kelvin/data/kelvinc.exe
kelvin-3.3.0.data/purelib/kelvin/data/kelvinw.exe
kelvin-3.3.0.dist-info/METADATA
kelvin-3.3.0.dist-info/WHEEL
kelvin-3.3.0.dist-info/top_level.txt
kelvin-3.3.0.dist-info/RECORD
