Metadata-Version: 2.1
Name: kelvin
Version: 3.3.0
Summary: Freezes Python scripts into Windows apps
Home-page: http://www.gitlab.com/mkleehammer/kelvin
Author: Michael Kleehammer
Author-email: michael@kleehammer.com
License: UNKNOWN
Platform: UNKNOWN
Classifier: Development Status :: 3 - Alpha
Classifier: Intended Audience :: Developers
Classifier: License :: OSI Approved :: MIT License
Classifier: Operating System :: Microsoft :: Windows
Classifier: Programming Language :: Python
Classifier: Programming Language :: Python :: 3
